trueroll/__init__.py
trueroll/__main__.py
trueroll/alley.py
trueroll/bowler.py
trueroll/bowling_database.py
trueroll/game.py
trueroll/league.py
trueroll/scoring.py
trueroll/tournament.py
trueroll/cli/__init__.py
trueroll/cli/commands.py
trueroll/tui/__init__.py
trueroll/tui/app.py
trueroll/web/__init__.py
trueroll/web/app.py
trueroll-0.2.1.dist-info/licenses/LICENSE
trueroll-0.2.1.dist-info/METADATA
trueroll-0.2.1.dist-info/WHEEL
trueroll-0.2.1.dist-info/entry_points.txt
trueroll-0.2.1.dist-info/top_level.txt
trueroll-0.2.1.dist-info/RECORD
